AUTHORS.rst
CONTRIBUTING.rst
HISTORY.rst
LICENSE
MANIFEST.in
README.rst
setup.py
greencard/__init__.py
greencard/greencard.py
greencard.egg-info/PKG-INFO
greencard.egg-info/SOURCES.txt
greencard.egg-info/dependency_links.txt
greencard.egg-info/entry_points.txt
greencard.egg-info/not-zip-safe
greencard.egg-info/requires.txt
greencard.egg-info/top_level.txt