Metadata-Version: 1.1
Name: greencard
Version: 0.2.1
Summary: Cookiecutter template for a Python package.
Home-page: https://github.com/Nekroze/greencard
Author: Taylor "Nekroze" Lawson
Author-email: nekroze@eturnilnetwork.com
License: MIT
Keywords: greencard
Platform: UNKNOWN
Classifier: Development Status :: 2 - Pre-Alpha
Classifier: Intended Audience :: Developers
Classifier: License :: OSI Approved :: MIT License
Classifier: Natural Language :: English
Classifier: Programming Language :: Python :: 2
Classifier: Programming Language :: Python :: 2.7
Classifier: Programming Language :: Python :: 3
Classifier: Programming Language :: Python :: 3.3
